robot/constant.py
robot/device.py
robot/exception.py
robot/finch.py
robot/finch_input.py
robot/finch_output.py
robot/hummingbird.py
robot/hummingbird_input.py
robot/hummingbird_output.py
robot/microbit.py
robot/microbit_input.py
robot/microbit_output.py
robot/request.py
robot/state.py
robot/utility.py
robot_birdbrain-0.14.1.dist-info/METADATA
robot_birdbrain-0.14.1.dist-info/WHEEL
robot_birdbrain-0.14.1.dist-info/licenses/AUTHORS.rst
robot_birdbrain-0.14.1.dist-info/licenses/LICENSE
robot_birdbrain-0.14.1.dist-info/RECORD
