Metadata-Version: 2.4
Name: robot-birdbrain
Version: 0.14.1
Summary: Rewritten Python Library for Birdbrain Technologies Hummingbird Bit and Finch 2.
Project-URL: Documentation, https://github.com/fmorton/robot-birdbrain#readme
Project-URL: Issues, https://github.com/fmorton/robot-birdbrain/issues
Project-URL: Source, https://github.com/fmorton/robot-birdbrain
Author-email: Frank Morton <fmorton@mac.com>
License-Expression: LGPL-3.0-only
License-File: AUTHORS.rst
License-File: LICENSE
Classifier: Development Status :: 4 - Beta
Classifier: Programming Language :: Python
Classifier: Programming Language :: Python :: 3.9
Classifier: Programming Language :: Python :: 3.10
Classifier: Programming Language :: Python :: 3.11
Classifier: Programming Language :: Python :: 3.12
Classifier: Programming Language :: Python :: 3.13
Classifier: Programming Language :: Python :: Implementation :: CPython
Classifier: Programming Language :: Python :: Implementation :: PyPy
Requires-Python: >=3.9
Provides-Extra: dev
Requires-Dist: black; extra == 'dev'
Requires-Dist: flake8; extra == 'dev'
Requires-Dist: pylint; extra == 'dev'
Requires-Dist: pytest; extra == 'dev'
Requires-Dist: pytest-mock; extra == 'dev'
Provides-Extra: test
Requires-Dist: flake8-pyproject; extra == 'test'
Requires-Dist: pytest-cov; extra == 'test'
Requires-Dist: pytest-mock; extra == 'test'
Requires-Dist: pytest>=8.3; extra == 'test'
